pajamas/__init__.py
pajamas-0.1a2.data/scripts/ipynb2pajamas
pajamas-0.1a2.data/scripts/ipynb_strip
pajamas-0.1a2.data/scripts/pajamas2ipynb
pajamas-0.1a2.dist-info/LICENSE
pajamas-0.1a2.dist-info/METADATA
pajamas-0.1a2.dist-info/WHEEL
pajamas-0.1a2.dist-info/top_level.txt
pajamas-0.1a2.dist-info/RECORD
