Metadata-Version: 2.1
Name: pajamas
Version: 0.1a2
Summary: Package to strip jupyter notebooks of their output and dress back up from these pajamas.
Home-page: https://github.com/barceloco/pajamas
Author: Armand Niederberger
Author-email: pajamas@armandniederberger.com
License: LICENSE
Platform: UNKNOWN
Classifier: Programming Language :: Python :: 3
Classifier: License :: OSI Approved :: MIT License
Classifier: Operating System :: OS Independent
